modeldb/__init__.py
modeldb/__main__.py
modeldb/Keras_Native/KerasModelDBSynceer.py
modeldb/Keras_Native/__init__.py
modeldb/basic/ModelDbSyncerBase.py
modeldb/basic/Structs.py
modeldb/basic/__init__.py
modeldb/events/Event.py
modeldb/events/ExperimentEvent.py
modeldb/events/ExperimentRunEvent.py
modeldb/events/FitEvent.py
modeldb/events/GridSearchCVEvent.py
modeldb/events/MetricEvent.py
modeldb/events/PipelineEvent.py
modeldb/events/ProjectEvent.py
modeldb/events/RandomSplitEvent.py
modeldb/events/TransformEvent.py
modeldb/events/__init__.py
modeldb/mxnet_native/MxnetModelDBSyncer.py
modeldb/mxnet_native/__init__.py
modeldb/nlp_native/NLPModelDBSyncer.py
modeldb/nlp_native/__init__.py
modeldb/pyspark_native/SparkModelDBSyncer.py
modeldb/pyspark_native/__init__.py
modeldb/sklearn_native/CrossValidationScore.py
modeldb/sklearn_native/GridCrossValidation.py
modeldb/sklearn_native/ModelDbSyncer.py
modeldb/sklearn_native/SyncableMetrics.py
modeldb/sklearn_native/SyncableRandomSplit.py
modeldb/sklearn_native/__init__.py
modeldb/tensorflow_native/TFModelDBSyncer.py
modeldb/tensorflow_native/__init__.py
modeldb/thrift/__init__.py
modeldb/thrift/modeldb/ModelDBService.py
modeldb/thrift/modeldb/__init__.py
modeldb/thrift/modeldb/constants.py
modeldb/thrift/modeldb/ttypes.py
modeldb/utils/ConfigUtils.py
modeldb/utils/MetadataConstants.py
modeldb/utils/Singleton.py
modeldb/utils/__init__.py
modeldb/xgb_native/GridFSEvent.py
modeldb/xgb_native/XGBModelDBSyncer.py
modeldb/xgb_native/XGBSyncableMetrics.py
modeldb/xgb_native/__init__.py
modeldb/xgb_native/modeldbQuery.py
modeldb_community-1.4.1.dist-info/METADATA
modeldb_community-1.4.1.dist-info/RECORD
modeldb_community-1.4.1.dist-info/WHEEL
modeldb_community-1.4.1.dist-info/entry_points.txt
modeldb_community-1.4.1.dist-info/top_level.txt
samples/__init__.py
samples/sklearn/GridSearchCrossValidation.py
samples/sklearn/Iris-RandomForest.py
samples/sklearn/LabelEncoding.py
samples/sklearn/LinearModel.py
samples/sklearn/OneHotEncoding.py
samples/sklearn/OttoGroup-Calibration.py
samples/sklearn/Pipeline-AnovaFilter.py
samples/sklearn/Pipeline-CensusDataset.py
