Metadata-Version: 2.1
Name: modeldb-community
Version: 1.4.1
Summary: A system to manage machine learning models for xgboost pyspark tensorflow sklearn keras
Home-page: https://github.com/mitdbg/modeldb/tree/master/client
Author: Manasi Vartak, MIT DB Group
Author-email: modeldb@csail.mit.edu
License: MIT
Keywords: machine learning ML model catalog
Platform: UNKNOWN
Classifier: Development Status :: 3 - Alpha
Classifier: Intended Audience :: Developers
Classifier: Intended Audience :: Science/Research
Classifier: Topic :: Scientific/Engineering
Classifier: License :: OSI Approved :: MIT License
Classifier: Programming Language :: Python :: 2.7
Classifier: Programming Language :: Python :: 3.5
Requires-Dist: numpy
Requires-Dist: pandas
Requires-Dist: statsmodels
Requires-Dist: matplotlib
Requires-Dist: patsy
Requires-Dist: scikit-learn
Requires-Dist: sklearn
Requires-Dist: thrift
Requires-Dist: pyyaml
Requires-Dist: requests
Requires-Dist: dpath
Requires-Dist: future
Requires-Dist: pymongo
Requires-Dist: xgboost
Requires-Dist: pymysql
